{
	"info": {
		"_postman_id": "92780b72-ba11-408d-9041-474b4f2c9cc3",
		"name": "Intelitrader",
		"schema": "https://schema.getpostman.com/json/collection/v2.1.0/collection.json"
	},
	"item": [
		{
			"name": "ListarUsuarios",
			"request": {
				"method": "GET",
				"header": [],
				"url": {
					"raw": "http://localhost:8001/api/Usuario/Listar",
					"protocol": "http",
					"host": [
						"localhost"
					],
					"port": "8001",
					"path": [
						"api",
						"Usuario",
						"Listar"
					]
				}
			},
			"response": []
		},
		{
			"name": "Cadastrar",
			"request": {
				"method": "POST",
				"header": [],
				"body": {
					"mode": "raw",
					"raw": "{\r\n   \"firstName\": \"FirsLog\",\r\n   \"surname\" : \"SurLog\",\r\n   \"age\": 65\r\n}",
					"options": {
						"raw": {
							"language": "json"
						}
					}
				},
				"url": {
					"raw": "http://localhost:8001/api/Usuario/Cadastrar",
					"protocol": "http",
					"host": [
						"localhost"
					],
					"port": "8001",
					"path": [
						"api",
						"Usuario",
						"Cadastrar"
					]
				}
			},
			"response": []
		},
		{
			"name": "Atualizar",
			"request": {
				"method": "PUT",
				"header": [],
				"body": {
					"mode": "raw",
					"raw": "{\r\n   \"firstName\": \"Fabio\",\r\n   \"surname\" : \"Miguel\",\r\n   \"age\": 45\r\n}",
					"options": {
						"raw": {
							"language": "json"
						}
					}
				},
				"url": {
					"raw": "http://localhost:8001/api/Usuario/Atualizar/dJ3z6Y",
					"protocol": "http",
					"host": [
						"localhost"
					],
					"port": "8001",
					"path": [
						"api",
						"Usuario",
						"Atualizar",
						"dJ3z6Y"
					]
				}
			},
			"response": []
		},
		{
			"name": "Deletar",
			"request": {
				"method": "DELETE",
				"header": [],
				"url": {
					"raw": "http://localhost:8001/api/Usuario/Deletar/9PH3T0",
					"protocol": "http",
					"host": [
						"localhost"
					],
					"port": "8001",
					"path": [
						"api",
						"Usuario",
						"Deletar",
						"9PH3T0"
					]
				}
			},
			"response": []
		}
	]
}